example/__init__.py
pf_pweb_sourceman/__init__.py
pf_pweb_sourceman/cli_main.py
pf_pweb_sourceman/common/__init__.py
pf_pweb_sourceman/common/console.py
pf_pweb_sourceman/common/constant.py
pf_pweb_sourceman/common/pcli.py
pf_pweb_sourceman/common/pwebsm_util.py
pf_pweb_sourceman/module/__init__.py
pf_pweb_sourceman/module/create_py_module.py
pf_pweb_sourceman/module/create_react_module.py
pf_pweb_sourceman/module/module_crud.py
pf_pweb_sourceman/node/__init__.py
pf_pweb_sourceman/node/lerna_json.py
pf_pweb_sourceman/node/package_json.py
pf_pweb_sourceman/prod/__init__.py
pf_pweb_sourceman/prod/pweb_deployer.py
pf_pweb_sourceman/pwebsm/__init__.py
pf_pweb_sourceman/pwebsm/descriptor_const.py
pf_pweb_sourceman/pwebsm/pwebsm_descriptor_creator.py
pf_pweb_sourceman/pwebsm/pwebsm_resolver.py
pf_pweb_sourceman/task/__init__.py
pf_pweb_sourceman/task/git_repo_man.py
pf_pweb_sourceman/task/project_init.py
pf_pweb_sourceman/task/project_manager.py
PF_PWeb_SourceMan-1.0.6.dist-info/LICENSE
PF_PWeb_SourceMan-1.0.6.dist-info/METADATA
PF_PWeb_SourceMan-1.0.6.dist-info/WHEEL
PF_PWeb_SourceMan-1.0.6.dist-info/entry_points.txt
PF_PWeb_SourceMan-1.0.6.dist-info/top_level.txt
PF_PWeb_SourceMan-1.0.6.dist-info/RECORD
