Metadata-Version: 2.1
Name: PF-PWeb-SourceMan
Version: 1.0.6
Summary: PWeb Project source management tool by Problem Fighter
Home-page: https://github.com/problemfighter/pf-pweb-sourceman
Author: Problem Fighter
Author-email: problemfighter.com@gmail.com
License: Apache 2.0
Platform: any
Classifier: Intended Audience :: Developers
Classifier: License :: OSI Approved :: Apache Software License
Classifier: Programming Language :: Python
Requires-Dist: virtualenv
Requires-Dist: GitPython
Requires-Dist: click
Requires-Dist: PF-PY-YMLEnv
Requires-Dist: PF-PY-File
Requires-Dist: PF-PY-Text
